{
  "object": "list",
  "count": 65,
  "data": [
    {
      "age": 28,
      "birthdate": "1985-03-10T00:00:00.000Z",
      "gender": "Female",
      "height": 1.74,
      "id": "beixing_wang",
      "image": "http://gtcdn.sochi2014.com/athlete/a/60/2009260-168X210.jpg",
      "name": "Beixing Wang",
      "weight": 66,
      "medals": {
        "gold": 0,
        "silver": 0,
        "bronze": 0,
        "total": 0
      },
      "sport": {
        "id": "speed_skating",
        "name": "Speed Skating"
      },
      "country": {
        "id": "china",
        "name": "China"
      }
    },
    {
      "age": 29,
      "birthdate": "1984-07-07T00:00:00.000Z",
      "gender": "Female",
      "height": 1.64,
      "id": "bingyu_wang",
      "image": "http://gtcdn.sochi2014.com/athlete/a/15/2004515-168X210.jpg",
      "name": "Bingyu Wang",
      "weight": null,
      "medals": {
        "gold": 0,
        "silver": 0,
        "bronze": 0,
        "total": 0
      },
      "sport": {
        "id": "curling",
        "name": "Curling"
      },
      "country": {
        "id": "china",
        "name": "China"
      }
    },
    {
      "age": 26,
      "birthdate": "1987-09-07T00:00:00.000Z",
      "gender": "Male",
      "height": 1.75,
      "id": "chao_wu",
      "image": "http://gtcdn.sochi2014.com/athlete/a/36/2016836-168X210.jpg",
      "name": "Chao Wu",
      "weight": 65,
      "medals": {
        "gold": 0,
        "silver": 0,
        "bronze": 0,
        "total": 0
      },
      "sport": {
        "id": "freestyle_skiing",
        "name": "Freestyle Skiing"
      },
      "country": {
        "id": "china",
        "name": "China"
      }
    },
    {
      "age": 22,
      "birthdate": "1991-03-21T00:00:00.000Z",
      "gender": "Female",
      "height": 1.7,
      "id": "chaoqing_song",
      "image": "http://gtcdn.sochi2014.com/athlete/a/51/2007851-168X210.jpg",
      "name": "Chaoqing Song",
      "weight": 60,
      "medals": {
        "gold": 0,
        "silver": 0,
        "bronze": 0,
        "total": 0
      },
      "sport": {
        "id": "biathlon",
        "name": "Biathlon"
      },
      "country": {
        "id": "china",
        "name": "China"
      }
    },
    {
      "age": 16,
      "birthdate": "1997-04-23T00:00:00.000Z",
      "gender": "Female",
      "height": 1.57,
      "id": "cheng_peng",
      "image": "http://gtcdn.sochi2014.com/athlete/a/48/2007248-168X210.jpg",
      "name": "Cheng Peng",
      "weight": null,
      "medals": {
        "gold": 0,
        "silver": 0,
        "bronze": 0,
        "total": 0
      },
      "sport": {
        "id": "figure_skating",
        "name": "Figure Skating"
      },
      "country": {
        "id": "china",
        "name": "China"
      }
    },
    {
      "age": 19,
      "birthdate": "1994-07-24T00:00:00.000Z",
      "gender": "Male",
      "height": null,
      "id": "dajing_wu",
      "image": "http://gtcdn.sochi2014.com/athlete/a/68/2014768-168X210.jpg",
      "name": "Dajing Wu",
      "weight": null,
      "medals": {
        "gold": 0,
        "silver": 1,
        "bronze": 1,
        "total": 2
      },
      "sport": {
        "id": "short_track",
        "name": "Short Track"
      },
      "country": {
        "id": "china",
        "name": "China"
      }
    },
    {
      "age": 27,
      "birthdate": "1986-05-12T00:00:00.000Z",
      "gender": "Female",
      "height": 1.66,
      "id": "dan_li",
      "image": "http://gtcdn.sochi2014.com/athlete/a/75/2031975-168X210.jpg",
      "name": "Dan Li",
      "weight": 62,
      "medals": {
        "gold": 0,
        "silver": 0,
        "bronze": 0,
        "total": 0
      },
      "sport": {
        "id": "speed_skating",
        "name": "Speed Skating"
      },
      "country": {
        "id": "china",
        "name": "China"
      }
    },
    {
      "age": 24,
      "birthdate": "1989-05-05T00:00:00.000Z",
      "gender": "Female",
      "height": 1.64,
      "id": "dandan_man",
      "image": "http://gtcdn.sochi2014.com/athlete/a/60/2007060-168X210.jpg",
      "name": "Dandan Man",
      "weight": 53,
      "medals": {
        "gold": 0,
        "silver": 0,
        "bronze": 0,
        "total": 0
      },
      "sport": {
        "id": "cross-country",
        "name": "Cross-Country"
      },
      "country": {
        "id": "china",
        "name": "China"
      }
    },
    {
      "age": 30,
      "birthdate": "1983-07-04T00:00:00.000Z",
      "gender": "Male",
      "height": 1.74,
      "id": "dejia_zou",
      "image": "http://gtcdn.sochi2014.com/athlete/a/47/2005047-168X210.jpg",
      "name": "Dejia Zou",
      "weight": null,
      "medals": {
        "gold": 0,
        "silver": 0,
        "bronze": 0,
        "total": 0
      },
      "sport": {
        "id": "curling",
        "name": "Curling"
      },
      "country": {
        "id": "china",
        "name": "China"
      }
    },
    {
      "age": 18,
      "birthdate": "1995-08-30T00:00:00.000Z",
      "gender": "Male",
      "height": null,
      "id": "dequan_chen",
      "image": "http://gtcdn.sochi2014.com/athlete/a/30/2014730-168X210.jpg",
      "name": "Dequan Chen",
      "weight": null,
      "medals": {
        "gold": 0,
        "silver": 0,
        "bronze": 1,
        "total": 1
      },
      "sport": {
        "id": "short_track",
        "name": "Short Track"
      },
      "country": {
        "id": "china",
        "name": "China"
      }
    },
    {
      "age": 23,
      "birthdate": "1990-06-14T00:00:00.000Z",
      "gender": "Male",
      "height": 1.85,
      "id": "dexin_ba",
      "image": "http://gtcdn.sochi2014.com/athlete/a/38/2005038-168X210.jpg",
      "name": "Dexin Ba",
      "weight": null,
      "medals": {
        "gold": 0,
        "silver": 0,
        "bronze": 0,
        "total": 0
      },
      "sport": {
        "id": "curling",
        "name": "Curling"
      },
      "country": {
        "id": "china",
        "name": "China"
      }
    },
    {
      "age": 23,
      "birthdate": "1990-10-20T00:00:00.000Z",
      "gender": "Male",
      "height": 1.73,
      "id": "guangpu_qi",
      "image": "http://gtcdn.sochi2014.com/athlete/a/19/2016819-168X210.jpg",
      "name": "Guangpu Qi",
      "weight": 64,
      "medals": {
        "gold": 0,
        "silver": 0,
        "bronze": 0,
        "total": 0
      },
      "sport": {
        "id": "freestyle_skiing",
        "name": "Freestyle Skiing"
      },
      "country": {
        "id": "china",
        "name": "China"
      }
    },
    {
      "age": 23,
      "birthdate": "1990-03-10T00:00:00.000Z",
      "gender": "Male",
      "height": 1.88,
      "id": "guojun_tian",
      "image": "http://gtcdn.sochi2014.com/athlete/a/99/2035599-168X210.jpg",
      "name": "Guojun Tian",
      "weight": 84,
      "medals": {
        "gold": 0,
        "silver": 0,
        "bronze": 0,
        "total": 0
      },
      "sport": {
        "id": "speed_skating",
        "name": "Speed Skating"
      },
      "country": {
        "id": "china",
        "name": "China"
      }
    },
    {
      "age": 17,
      "birthdate": "1996-03-06T00:00:00.000Z",
      "gender": "Male",
      "height": 1.69,
      "id": "han_yan",
      "image": "http://gtcdn.sochi2014.com/athlete/a/54/2007254-168X210.jpg",
      "name": "Han Yan",
      "weight": null,
      "medals": {
        "gold": 0,
        "silver": 0,
        "bronze": 0,
        "total": 0
      },
      "sport": {
        "id": "figure_skating",
        "name": "Figure Skating"
      },
      "country": {
        "id": "china",
        "name": "China"
      }
    },
    {
      "age": 29,
      "birthdate": "1984-07-06T00:00:00.000Z",
      "gender": "Male",
      "height": 1.81,
      "id": "hao_zhang",
      "image": "http://gtcdn.sochi2014.com/athlete/a/50/2007250-168X210.jpg",
      "name": "Hao Zhang",
      "weight": null,
      "medals": {
        "gold": 0,
        "silver": 0,
        "bronze": 0,
        "total": 0
      },
      "sport": {
        "id": "figure_skating",
        "name": "Figure Skating"
      },
      "country": {
        "id": "china",
        "name": "China"
      }
    },
    {
      "age": 25,
      "birthdate": "1988-04-12T00:00:00.000Z",
      "gender": "Female",
      "height": 1.74,
      "id": "hong_zhang",
      "image": "http://gtcdn.sochi2014.com/athlete/a/20/2031820-168X210.jpg",
      "name": "Hong Zhang",
      "weight": 65,
      "medals": {
        "gold": 1,
        "silver": 0,
        "bronze": 0,
        "total": 1
      },
      "sport": {
        "id": "speed_skating",
        "name": "Speed Skating"
      },
      "country": {
        "id": "china",
        "name": "China"
      }
    },
    {
      "age": 29,
      "birthdate": "1984-03-09T00:00:00.000Z",
      "gender": "Female",
      "height": 1.6,
      "id": "hongxue_li",
      "image": "http://gtcdn.sochi2014.com/athlete/a/57/2007057-168X210.jpg",
      "name": "Hongxue Li",
      "weight": 52,
      "medals": {
        "gold": 0,
        "silver": 0,
        "bronze": 0,
        "total": 0
      },
      "sport": {
        "id": "cross-country",
        "name": "Cross-Country"
      },
      "country": {
        "id": "china",
        "name": "China"
      }
    },
    {
      "age": 26,
      "birthdate": "1988-01-12T00:00:00.000Z",
      "gender": "Male",
      "height": 1.75,
      "id": "jialiang_zang",
      "image": "http://gtcdn.sochi2014.com/athlete/a/40/2005040-168X210.jpg",
      "name": "Jialiang Zang",
      "weight": null,
      "medals": {
        "gold": 0,
        "silver": 0,
        "bronze": 0,
        "total": 0
      },
      "sport": {
        "id": "curling",
        "name": "Curling"
      },
      "country": {
        "id": "china",
        "name": "China"
      }
    },
    {
      "age": 22,
      "birthdate": "1991-11-05T00:00:00.000Z",
      "gender": "Female",
      "height": 1.68,
      "id": "jialin_tang",
      "image": "http://gtcdn.sochi2014.com/athlete/a/49/2007849-168X210.jpg",
      "name": "Jialin Tang",
      "weight": 55,
      "medals": {
        "gold": 0,
        "silver": 0,
        "bronze": 0,
        "total": 0
      },
      "sport": {
        "id": "biathlon",
        "name": "Biathlon"
      },
      "country": {
        "id": "china",
        "name": "China"
      }
    },
    {
      "age": 34,
      "birthdate": "1979-08-15T00:00:00.000Z",
      "gender": "Male",
      "height": 1.79,
      "id": "jian_tong",
      "image": "http://gtcdn.sochi2014.com/athlete/a/52/2007252-168X210.jpg",
      "name": "Jian Tong",
      "weight": null,
      "medals": {
        "gold": 0,
        "silver": 0,
        "bronze": 0,
        "total": 0
      },
      "sport": {
        "id": "figure_skating",
        "name": "Figure Skating"
      },
      "country": {
        "id": "china",
        "name": "China"
      }
    },
    {
      "age": 27,
      "birthdate": "1986-08-15T00:00:00.000Z",
      "gender": "Female",
      "height": 1.6,
      "id": "jianrou_li",
      "image": "http://gtcdn.sochi2014.com/athlete/a/17/2014817-168X210.jpg",
      "name": "Jianrou Li",
      "weight": 53,
      "medals": {
        "gold": 1,
        "silver": 0,
        "bronze": 0,
        "total": 1
      },
      "sport": {
        "id": "short_track",
        "name": "Short Track"
      },
      "country": {
        "id": "china",
        "name": "China"
      }
    },
    {
      "age": 21,
      "birthdate": "1992-09-17T00:00:00.000Z",
      "gender": "Female",
      "height": 1.72,
      "id": "jiayu_liu",
      "image": "http://gtcdn.sochi2014.com/athlete/a/90/2005890-168X210.jpg",
      "name": "Jiayu Liu",
      "weight": 65,
      "medals": {
        "gold": 0,
        "silver": 0,
        "bronze": 0,
        "total": 0
      },
      "sport": {
        "id": "snowboard",
        "name": "Snowboard"
      },
      "country": {
        "id": "china",
        "name": "China"
      }
    },
    {
      "age": 19,
      "birthdate": "1994-04-07T00:00:00.000Z",
      "gender": "Male",
      "height": 1.75,
      "id": "jingnan_shi",
      "image": "http://gtcdn.sochi2014.com/athlete/a/18/2022318-168X210.jpg",
      "name": "Jingnan Shi",
      "weight": 66,
      "medals": {
        "gold": 0,
        "silver": 0,
        "bronze": 1,
        "total": 1
      },
      "sport": {
        "id": "short_track",
        "name": "Short Track"
      },
      "country": {
        "id": "china",
        "name": "China"
      }
    },
    {
      "age": 20,
      "birthdate": "1993-09-19T00:00:00.000Z",
      "gender": "Female",
      "height": 1.72,
      "id": "kexin_fan",
      "image": "http://gtcdn.sochi2014.com/athlete/a/09/2014809-168X210.jpg",
      "name": "Kexin Fan",
      "weight": 55,
      "medals": {
        "gold": 0,
        "silver": 1,
        "bronze": 0,
        "total": 1
      },
      "sport": {
        "id": "short_track",
        "name": "Short Track"
      },
      "country": {
        "id": "china",
        "name": "China"
      }
    },
    {
      "age": 18,
      "birthdate": "1995-10-17T00:00:00.000Z",
      "gender": "Female",
      "height": 1.53,
      "id": "kexin_zhang",
      "image": "http://gtcdn.sochi2014.com/athlete/a/67/2007167-168X210.jpg",
      "name": "Kexin Zhang",
      "weight": null,
      "medals": {
        "gold": 0,
        "silver": 0,
        "bronze": 0,
        "total": 0
      },
      "sport": {
        "id": "figure_skating",
        "name": "Figure Skating"
      },
      "country": {
        "id": "china",
        "name": "China"
      }
    },
    {
      "age": 26,
      "birthdate": "1987-10-26T00:00:00.000Z",
      "gender": "Female",
      "height": 1.65,
      "id": "lina_xia",
      "image": "http://gtcdn.sochi2014.com/athlete/a/46/2009846-168X210.jpg",
      "name": "Lina Xia",
      "weight": 63,
      "medals": {
        "gold": 0,
        "silver": 0,
        "bronze": 0,
        "total": 0
      },
      "sport": {
        "id": "alpine_skiing",
        "name": "Alpine Skiing"
      },
      "country": {
        "id": "china",
        "name": "China"
      }
    },
    {
      "age": 25,
      "birthdate": "1988-12-21T00:00:00.000Z",
      "gender": "Male",
      "height": 1.68,
      "id": "long_ren",
      "image": "http://gtcdn.sochi2014.com/athlete/a/33/2007533-168X210.jpg",
      "name": "Long Ren",
      "weight": 64,
      "medals": {
        "gold": 0,
        "silver": 0,
        "bronze": 0,
        "total": 0
      },
      "sport": {
        "id": "biathlon",
        "name": "Biathlon"
      },
      "country": {
        "id": "china",
        "name": "China"
      }
    },
    {
      "age": 23,
      "birthdate": "1990-07-12T00:00:00.000Z",
      "gender": "Female",
      "height": null,
      "id": "mengtao_xu",
      "image": "http://gtcdn.sochi2014.com/athlete/a/68/2016768-168X210.jpg",
      "name": "Mengtao Xu",
      "weight": null,
      "medals": {
        "gold": 0,
        "silver": 1,
        "bronze": 0,
        "total": 1
      },
      "sport": {
        "id": "freestyle_skiing",
        "name": "Freestyle Skiing"
      },
      "country": {
        "id": "china",
        "name": "China"
      }
    },
    {
      "age": 18,
      "birthdate": "1995-08-30T00:00:00.000Z",
      "gender": "Female",
      "height": 1.66,
      "id": "na_song",
      "image": "http://gtcdn.sochi2014.com/athlete/a/54/2007854-168X210.jpg",
      "name": "Na Song",
      "weight": 57,
      "medals": {
        "gold": 0,
        "silver": 0,
        "bronze": 0,
        "total": 0
      },
      "sport": {
        "id": "biathlon",
        "name": "Biathlon"
      },
      "country": {
        "id": "china",
        "name": "China"
      }
    },
    {
      "age": 31,
      "birthdate": "1983-01-10T00:00:00.000Z",
      "gender": "Female",
      "height": 1.61,
      "id": "nina_li",
      "image": "http://gtcdn.sochi2014.com/athlete/a/64/2016764-168X210.jpg",
      "name": "Nina Li",
      "weight": 48,
      "medals": {
        "gold": 0,
        "silver": 0,
        "bronze": 0,
        "total": 0
      },
      "sport": {
        "id": "freestyle_skiing",
        "name": "Freestyle Skiing"
      },
      "country": {
        "id": "china",
        "name": "China"
      }
    },
    {
      "age": 22,
      "birthdate": "1992-01-07T00:00:00.000Z",
      "gender": "Female",
      "height": 1.62,
      "id": "qin_ning",
      "image": "http://gtcdn.sochi2014.com/athlete/a/21/2001221-168X210.jpg",
      "name": "Qin Ning",
      "weight": 60,
      "medals": {
        "gold": 0,
        "silver": 0,
        "bronze": 0,
        "total": 0
      },
      "sport": {
        "id": "freestyle_skiing",
        "name": "Freestyle Skiing"
      },
      "country": {
        "id": "china",
        "name": "China"
      }
    },
    {
      "age": 34,
      "birthdate": "1979-12-24T00:00:00.000Z",
      "gender": "Female",
      "height": 1.6,
      "id": "qing_pang",
      "image": "http://gtcdn.sochi2014.com/athlete/a/51/2007251-168X210.jpg",
      "name": "Qing Pang",
      "weight": null,
      "medals": {
        "gold": 0,
        "silver": 0,
        "bronze": 0,
        "total": 0
      },
      "sport": {
        "id": "figure_skating",
        "name": "Figure Skating"
      },
      "country": {
        "id": "china",
        "name": "China"
      }
    },
    {
      "age": 26,
      "birthdate": "1988-01-18T00:00:00.000Z",
      "gender": "Male",
      "height": 1.88,
      "id": "qinghai_sun",
      "image": "http://gtcdn.sochi2014.com/athlete/a/54/2007054-168X210.jpg",
      "name": "Qinghai Sun",
      "weight": 80,
      "medals": {
        "gold": 0,
        "silver": 0,
        "bronze": 0,
        "total": 0
      },
      "sport": {
        "id": "cross-country",
        "name": "Cross-Country"
      },
      "country": {
        "id": "china",
        "name": "China"
      }
    },
    {
      "age": 28,
      "birthdate": "1985-10-05T00:00:00.000Z",
      "gender": "Female",
      "height": 1.67,
      "id": "qingshuang_yue",
      "image": "http://gtcdn.sochi2014.com/athlete/a/19/2004519-168X210.jpg",
      "name": "Qingshuang Yue",
      "weight": null,
      "medals": {
        "gold": 0,
        "silver": 0,
        "bronze": 0,
        "total": 0
      },
      "sport": {
        "id": "curling",
        "name": "Curling"
      },
      "country": {
        "id": "china",
        "name": "China"
      }
    },
    {
      "age": 20,
      "birthdate": "1993-08-16T00:00:00.000Z",
      "gender": "Female",
      "height": 1.75,
      "id": "qishi_li",
      "image": "http://gtcdn.sochi2014.com/athlete/a/66/2036566-168X210.jpg",
      "name": "Qishi Li",
      "weight": 68,
      "medals": {
        "gold": 0,
        "silver": 0,
        "bronze": 0,
        "total": 0
      },
      "sport": {
        "id": "speed_skating",
        "name": "Speed Skating"
      },
      "country": {
        "id": "china",
        "name": "China"
      }
    },
    {
      "age": 25,
      "birthdate": "1988-11-26T00:00:00.000Z",
      "gender": "Female",
      "height": 1.65,
      "id": "qiuhong_liu",
      "image": "http://gtcdn.sochi2014.com/athlete/a/89/2014789-168X210.jpg",
      "name": "Qiuhong Liu",
      "weight": 55,
      "medals": {
        "gold": 0,
        "silver": 0,
        "bronze": 0,
        "total": 0
      },
      "sport": {
        "id": "short_track",
        "name": "Short Track"
      },
      "country": {
        "id": "china",
        "name": "China"
      }
    },
    {
      "age": 19,
      "birthdate": "1994-08-30T00:00:00.000Z",
      "gender": "Male",
      "height": 1.73,
      "id": "qiuming_bai",
      "image": "http://gtcdn.sochi2014.com/athlete/a/82/2035182-168X210.jpg",
      "name": "Qiuming Bai",
      "weight": 70,
      "medals": {
        "gold": 0,
        "silver": 0,
        "bronze": 0,
        "total": 0
      },
      "sport": {
        "id": "speed_skating",
        "name": "Speed Skating"
      },
      "country": {
        "id": "china",
        "name": "China"
      }
    },
    {
      "age": 31,
      "birthdate": "1982-03-13T00:00:00.000Z",
      "gender": "Male",
      "height": 1.82,
      "id": "rui_liu",
      "image": "http://gtcdn.sochi2014.com/athlete/a/35/2005035-168X210.jpg",
      "name": "Rui Liu",
      "weight": null,
      "medals": {
        "gold": 0,
        "silver": 0,
        "bronze": 0,
        "total": 0
      },
      "sport": {
        "id": "curling",
        "name": "Curling"
      },
      "country": {
        "id": "china",
        "name": "China"
      }
    },
    {
      "age": 25,
      "birthdate": "1988-02-13T00:00:00.000Z",
      "gender": "Female",
      "height": 1.71,
      "id": "shuai_qi",
      "image": "http://gtcdn.sochi2014.com/athlete/a/69/2031969-168X210.jpg",
      "name": "Shuai Qi",
      "weight": 61,
      "medals": {
        "gold": 0,
        "silver": 0,
        "bronze": 0,
        "total": 0
      },
      "sport": {
        "id": "speed_skating",
        "name": "Speed Skating"
      },
      "country": {
        "id": "china",
        "name": "China"
      }
    },
    {
      "age": 26,
      "birthdate": "1987-02-11T00:00:00.000Z",
      "gender": "Female",
      "height": 1.62,
      "id": "shuang_cheng",
      "image": "http://gtcdn.sochi2014.com/athlete/a/78/2016778-168X210.jpg",
      "name": "Shuang Cheng",
      "weight": 46,
      "medals": {
        "gold": 0,
        "silver": 0,
        "bronze": 0,
        "total": 0
      },
      "sport": {
        "id": "freestyle_skiing",
        "name": "Freestyle Skiing"
      },
      "country": {
        "id": "china",
        "name": "China"
      }
    },
    {
      "age": 21,
      "birthdate": "1992-06-27T00:00:00.000Z",
      "gender": "Female",
      "height": 1.69,
      "id": "shuang_li",
      "image": "http://gtcdn.sochi2014.com/athlete/a/92/2005892-168X210.jpg",
      "name": "Shuang Li",
      "weight": 63,
      "medals": {
        "gold": 0,
        "silver": 0,
        "bronze": 0,
        "total": 0
      },
      "sport": {
        "id": "snowboard",
        "name": "Snowboard"
      },
      "country": {
        "id": "china",
        "name": "China"
      }
    },
    {
      "age": 27,
      "birthdate": "1986-09-10T00:00:00.000Z",
      "gender": "Female",
      "height": 1.72,
      "id": "shuang_zhang",
      "image": "http://gtcdn.sochi2014.com/athlete/a/88/2032388-168X210.jpg",
      "name": "Shuang Zhang",
      "weight": 70,
      "medals": {
        "gold": 0,
        "silver": 0,
        "bronze": 0,
        "total": 0
      },
      "sport": {
        "id": "speed_skating",
        "name": "Speed Skating"
      },
      "country": {
        "id": "china",
        "name": "China"
      }
    },
    {
      "age": 17,
      "birthdate": "1996-06-03T00:00:00.000Z",
      "gender": "Male",
      "height": 1.75,
      "id": "tianyu_han",
      "image": "http://gtcdn.sochi2014.com/athlete/a/37/2014737-168X210.jpg",
      "name": "Tianyu Han",
      "weight": 64,
      "medals": {
        "gold": 0,
        "silver": 1,
        "bronze": 1,
        "total": 2
      },
      "sport": {
        "id": "short_track",
        "name": "Short Track"
      },
      "country": {
        "id": "china",
        "name": "China"
      }
    },
    {
      "age": 23,
      "birthdate": "1990-08-13T00:00:00.000Z",
      "gender": "Male",
      "height": 1.79,
      "id": "wancheng_shi",
      "image": "http://gtcdn.sochi2014.com/athlete/a/95/2005895-168X210.jpg",
      "name": "Wancheng Shi",
      "weight": 78,
      "medals": {
        "gold": 0,
        "silver": 0,
        "bronze": 0,
        "total": 0
      },
      "sport": {
        "id": "snowboard",
        "name": "Snowboard"
      },
      "country": {
        "id": "china",
        "name": "China"
      }
    },
    {
      "age": 21,
      "birthdate": "1992-07-06T00:00:00.000Z",
      "gender": "Male",
      "height": 1.65,
      "id": "wenhao_liang",
      "image": "http://gtcdn.sochi2014.com/athlete/a/79/2014779-168X210.jpg",
      "name": "Wenhao Liang",
      "weight": 62,
      "medals": {
        "gold": 0,
        "silver": 0,
        "bronze": 0,
        "total": 0
      },
      "sport": {
        "id": "short_track",
        "name": "Short Track"
      },
      "country": {
        "id": "china",
        "name": "China"
      }
    },
    {
      "age": 26,
      "birthdate": "1987-02-27T00:00:00.000Z",
      "gender": "Male",
      "height": 1.72,
      "id": "wenlong_xu",
      "image": "http://gtcdn.sochi2014.com/athlete/a/55/2007055-168X210.jpg",
      "name": "Wenlong Xu",
      "weight": 67,
      "medals": {
        "gold": 0,
        "silver": 0,
        "bronze": 0,
        "total": 0
      },
      "sport": {
        "id": "cross-country",
        "name": "Cross-Country"
      },
      "country": {
        "id": "china",
        "name": "China"
      }
    },
    {
      "age": 29,
      "birthdate": "1984-09-14T00:00:00.000Z",
      "gender": "Male",
      "height": 1.78,
      "id": "xiaoming_xu",
      "image": "http://gtcdn.sochi2014.com/athlete/a/37/2005037-168X210.jpg",
      "name": "Xiaoming Xu",
      "weight": null,
      "medals": {
        "gold": 0,
        "silver": 0,
        "bronze": 0,
        "total": 0
      },
      "sport": {
        "id": "curling",
        "name": "Curling"
      },
      "country": {
        "id": "china",
        "name": "China"
      }
    },
    {
      "age": 28,
      "birthdate": "1985-08-04T00:00:00.000Z",
      "gender": "Female",
      "height": 1.65,
      "id": "xin_zhang",
      "image": "http://gtcdn.sochi2014.com/athlete/a/85/2016785-168X210.jpg",
      "name": "Xin Zhang",
      "weight": 56,
      "medals": {
        "gold": 0,
        "silver": 0,
        "bronze": 0,
        "total": 0
      },
      "sport": {
        "id": "freestyle_skiing",
        "name": "Freestyle Skiing"
      },
      "country": {
        "id": "china",
        "name": "China"
      }
    },
    {
      "age": 21,
      "birthdate": "1992-12-31T00:00:00.000Z",
      "gender": "Female",
      "height": 1.75,
      "id": "xin_zhao",
      "image": "http://gtcdn.sochi2014.com/athlete/a/67/2032467-168X210.jpg",
      "name": "Xin Zhao",
      "weight": 70,
      "medals": {
        "gold": 0,
        "silver": 0,
        "bronze": 0,
        "total": 0
      },
      "sport": {
        "id": "speed_skating",
        "name": "Speed Skating"
      },
      "country": {
        "id": "china",
        "name": "China"
      }
    },
    {
      "age": 27,
      "birthdate": "1987-01-26T00:00:00.000Z",
      "gender": "Female",
      "height": 1.65,
      "id": "xintong_huang",
      "image": "http://gtcdn.sochi2014.com/athlete/a/42/2007242-168X210.jpg",
      "name": "Xintong Huang",
      "weight": null,
      "medals": {
        "gold": 0,
        "silver": 0,
        "bronze": 0,
        "total": 0
      },
      "sport": {
        "id": "figure_skating",
        "name": "Figure Skating"
      },
      "country": {
        "id": "china",
        "name": "China"
      }
    },
    {
      "age": 22,
      "birthdate": "1991-08-26T00:00:00.000Z",
      "gender": "Female",
      "height": 1.7,
      "id": "xue_kong",
      "image": "http://gtcdn.sochi2014.com/athlete/a/23/2014823-168X210.jpg",
      "name": "Xue Kong",
      "weight": 59,
      "medals": {
        "gold": 0,
        "silver": 0,
        "bronze": 0,
        "total": 0
      },
      "sport": {
        "id": "short_track",
        "name": "Short Track"
      },
      "country": {
        "id": "china",
        "name": "China"
      }
    },
    {
      "age": 20,
      "birthdate": "1993-09-26T00:00:00.000Z",
      "gender": "Female",
      "height": 1.62,
      "id": "xuetong_cai",
      "image": "http://gtcdn.sochi2014.com/athlete/a/89/2005889-168X210.jpg",
      "name": "Xuetong Cai",
      "weight": 60,
      "medals": {
        "gold": 0,
        "silver": 0,
        "bronze": 0,
        "total": 0
      },
      "sport": {
        "id": "snowboard",
        "name": "Snowboard"
      },
      "country": {
        "id": "china",
        "name": "China"
      }
    },
    {
      "age": 26,
      "birthdate": "1987-08-21T00:00:00.000Z",
      "gender": "Male",
      "height": 1.88,
      "id": "xun_zheng",
      "image": "http://gtcdn.sochi2014.com/athlete/a/43/2007243-168X210.jpg",
      "name": "Xun Zheng",
      "weight": null,
      "medals": {
        "gold": 0,
        "silver": 0,
        "bronze": 0,
        "total": 0
      },
      "sport": {
        "id": "figure_skating",
        "name": "Figure Skating"
      },
      "country": {
        "id": "china",
        "name": "China"
      }
    },
    {
      "age": 21,
      "birthdate": "1992-05-10T00:00:00.000Z",
      "gender": "Female",
      "height": 1.63,
      "id": "yan_zhang",
      "image": "http://gtcdn.sochi2014.com/athlete/a/45/2007845-168X210.jpg",
      "name": "Yan Zhang",
      "weight": 48,
      "medals": {
        "gold": 0,
        "silver": 0,
        "bronze": 0,
        "total": 0
      },
      "sport": {
        "id": "biathlon",
        "name": "Biathlon"
      },
      "country": {
        "id": "china",
        "name": "China"
      }
    },
    {
      "age": 31,
      "birthdate": "1982-09-30T00:00:00.000Z",
      "gender": "Female",
      "height": 1.62,
      "id": "yan_zhou",
      "image": "http://gtcdn.sochi2014.com/athlete/a/20/2004520-168X210.jpg",
      "name": "Yan Zhou",
      "weight": null,
      "medals": {
        "gold": 0,
        "silver": 0,
        "bronze": 0,
        "total": 0
      },
      "sport": {
        "id": "curling",
        "name": "Curling"
      },
      "country": {
        "id": "china",
        "name": "China"
      }
    },
    {
      "age": 22,
      "birthdate": "1991-06-09T00:00:00.000Z",
      "gender": "Female",
      "height": 1.65,
      "id": "yang_zhou",
      "image": "http://gtcdn.sochi2014.com/athlete/a/53/2014753-168X210.jpg",
      "name": "Yang Zhou",
      "weight": 62,
      "medals": {
        "gold": 1,
        "silver": 0,
        "bronze": 0,
        "total": 1
      },
      "sport": {
        "id": "short_track",
        "name": "Short Track"
      },
      "country": {
        "id": "china",
        "name": "China"
      }
    },
    {
      "age": 20,
      "birthdate": "1993-12-02T00:00:00.000Z",
      "gender": "Female",
      "height": 1.63,
      "id": "yilun_jiang",
      "image": "http://gtcdn.sochi2014.com/athlete/a/26/2004526-168X210.jpg",
      "name": "Yilun Jiang",
      "weight": null,
      "medals": {
        "gold": 0,
        "silver": 0,
        "bronze": 0,
        "total": 0
      },
      "sport": {
        "id": "curling",
        "name": "Curling"
      },
      "country": {
        "id": "china",
        "name": "China"
      }
    },
    {
      "age": 32,
      "birthdate": "1981-08-19T00:00:00.000Z",
      "gender": "Female",
      "height": 1.65,
      "id": "yin_liu",
      "image": "http://gtcdn.sochi2014.com/athlete/a/16/2004516-168X210.jpg",
      "name": "Yin Liu",
      "weight": null,
      "medals": {
        "gold": 0,
        "silver": 0,
        "bronze": 0,
        "total": 0
      },
      "sport": {
        "id": "curling",
        "name": "Curling"
      },
      "country": {
        "id": "china",
        "name": "China"
      }
    },
    {
      "age": 21,
      "birthdate": "1992-10-03T00:00:00.000Z",
      "gender": "Male",
      "height": 1.72,
      "id": "yiwei_zhang",
      "image": "http://gtcdn.sochi2014.com/athlete/a/94/2005894-168X210.jpg",
      "name": "Yiwei Zhang",
      "weight": 68,
      "medals": {
        "gold": 0,
        "silver": 0,
        "bronze": 0,
        "total": 0
      },
      "sport": {
        "id": "snowboard",
        "name": "Snowboard"
      },
      "country": {
        "id": "china",
        "name": "China"
      }
    },
    {
      "age": 24,
      "birthdate": "1989-02-20T00:00:00.000Z",
      "gender": "Male",
      "height": 1.82,
      "id": "yuxin_zhang",
      "image": "http://gtcdn.sochi2014.com/athlete/a/52/2009852-168X210.jpg",
      "name": "Yuxin Zhang",
      "weight": 71,
      "medals": {
        "gold": 0,
        "silver": 0,
        "bronze": 0,
        "total": 0
      },
      "sport": {
        "id": "alpine_skiing",
        "name": "Alpine Skiing"
      },
      "country": {
        "id": "china",
        "name": "China"
      }
    },
    {
      "age": 22,
      "birthdate": "1991-07-17T00:00:00.000Z",
      "gender": "Female",
      "height": 1.58,
      "id": "zhifeng_sun",
      "image": "http://gtcdn.sochi2014.com/athlete/a/91/2005891-168X210.jpg",
      "name": "Zhifeng Sun",
      "weight": 58,
      "medals": {
        "gold": 0,
        "silver": 0,
        "bronze": 0,
        "total": 0
      },
      "sport": {
        "id": "snowboard",
        "name": "Snowboard"
      },
      "country": {
        "id": "china",
        "name": "China"
      }
    },
    {
      "age": 28,
      "birthdate": "1985-11-10T00:00:00.000Z",
      "gender": "Male",
      "height": 1.74,
      "id": "zhongqing_liu",
      "image": "http://gtcdn.sochi2014.com/athlete/a/28/2016828-168X210.jpg",
      "name": "Zhongqing Liu",
      "weight": 73,
      "medals": {
        "gold": 0,
        "silver": 0,
        "bronze": 0,
        "total": 0
      },
      "sport": {
        "id": "freestyle_skiing",
        "name": "Freestyle Skiing"
      },
      "country": {
        "id": "china",
        "name": "China"
      }
    },
    {
      "age": 22,
      "birthdate": "1991-07-26T00:00:00.000Z",
      "gender": "Male",
      "height": 1.93,
      "id": "zhongsheng_mu",
      "image": "http://gtcdn.sochi2014.com/athlete/a/96/2034596-168X210.jpg",
      "name": "Zhongsheng Mu",
      "weight": 83,
      "medals": {
        "gold": 0,
        "silver": 0,
        "bronze": 0,
        "total": 0
      },
      "sport": {
        "id": "speed_skating",
        "name": "Speed Skating"
      },
      "country": {
        "id": "china",
        "name": "China"
      }
    },
    {
      "age": 17,
      "birthdate": "1996-12-14T00:00:00.000Z",
      "gender": "Female",
      "height": 1.61,
      "id": "zijun_li",
      "image": "http://gtcdn.sochi2014.com/athlete/a/85/2007185-168X210.jpg",
      "name": "Zijun Li",
      "weight": null,
      "medals": {
        "gold": 0,
        "silver": 0,
        "bronze": 0,
        "total": 0
      },
      "sport": {
        "id": "figure_skating",
        "name": "Figure Skating"
      },
      "country": {
        "id": "china",
        "name": "China"
      }
    },
    {
      "age": 22,
      "birthdate": "1991-03-01T00:00:00.000Z",
      "gender": "Male",
      "height": 1.76,
      "id": "zongyang_jia",
      "image": "http://gtcdn.sochi2014.com/athlete/a/12/2016812-168X210.jpg",
      "name": "Zongyang Jia",
      "weight": 68,
      "medals": {
        "gold": 0,
        "silver": 0,
        "bronze": 1,
        "total": 1
      },
      "sport": {
        "id": "freestyle_skiing",
        "name": "Freestyle Skiing"
      },
      "country": {
        "id": "china",
        "name": "China"
      }
    }
  ]
}